probably/__init__.py
probably/bloomfilter.py
probably/cdbf.py
probably/countmin.py
probably/hashfunctions.py
probably/hll.py
probably/maintenance.cpython-39-darwin.so
probably/setup.py
probably/temporal_daily.py
probably-1.1.3.dist-info/LICENSE
probably-1.1.3.dist-info/METADATA
probably-1.1.3.dist-info/WHEEL
probably-1.1.3.dist-info/top_level.txt
probably-1.1.3.dist-info/RECORD
